[
  {
    "number": 0,
    "name": "The Fool",
    "suit": "major",
    "uprightDescription": "Lorem ipsum",
    "reverseDescription": "Lorem ipsum"
  },
  {
    "number": 1,
    "name": "The Magician",
    "suit": "major",
    "uprightDescription": "Lorem ipsum",
    "reverseDescription": "Lorem ipsum"
  },
  {
    "number": 2,
    "name": "The High Priestess",
    "suit": "major",
    "uprightDescription": "Lorem ipsum",
    "reverseDescription": "Lorem ipsum"
  },
  {
    "number": 3,
    "name": "The Empress",
    "suit": "major",
    "uprightDescription": "Lorem ipsum",
    "reverseDescription": "Lorem ipsum"
  },
  {
    "number": 4,
    "name": "The Emperor",
    "suit": "major",
    "uprightDescription": "Lorem ipsum",
    "reverseDescription": "Lorem ipsum"
  },
  {
    "number": 5,
    "name": "The Hierophant",
    "suit": "major",
    "uprightDescription": "Lorem ipsum",
    "reverseDescription": "Lorem ipsum"
  },
  {
    "number": 6,
    "name": "The Lovers",
    "suit": "major",
    "uprightDescription": "Lorem ipsum",
    "reverseDescription": "Lorem ipsum"
  },
  {
    "number": 7,
    "name": "The Chariot",
    "suit": "major",
    "uprightDescription": "Lorem ipsum",
    "reverseDescription": "Lorem ipsum"
  },
  {
    "number": 8,
    "name": "Strength",
    "suit": "major",
    "uprightDescription": "Lorem ipsum",
    "reverseDescription": "Lorem ipsum"
  },
  {
    "number": 9,
    "name": "The Hermit",
    "suit": "major",
    "uprightDescription": "Lorem ipsum",
    "reverseDescription": "Lorem ipsum"
  },
  {
    "number": 10,
    "name": "Wheel of Fortune",
    "suit": "major",
    "uprightDescription": "Lorem ipsum",
    "reverseDescription": "Lorem ipsum"
  },
  {
    "number": 11,
    "name": "Justice",
    "suit": "major",
    "uprightDescription": "Lorem ipsum",
    "reverseDescription": "Lorem ipsum"
  },
  {
    "number": 12,
    "name": "The Hanged Man",
    "suit": "major",
    "uprightDescription": "Lorem ipsum",
    "reverseDescription": "Lorem ipsum"
  },
  {
    "number": 13,
    "name": "Death",
    "suit": "major",
    "uprightDescription": "Lorem ipsum",
    "reverseDescription": "Lorem ipsum"
  },
  {
    "number": 14,
    "name": "Temperance",
    "suit": "major",
    "uprightDescription": "Lorem ipsum",
    "reverseDescription": "Lorem ipsum"
  },
  {
    "number": 15,
    "name": "The Devil",
    "suit": "major",
    "uprightDescription": "Lorem ipsum",
    "reverseDescription": "Lorem ipsum"
  },
  {
    "number": 16,
    "name": "The Tower",
    "suit": "major",
    "uprightDescription": "Lorem ipsum",
    "reverseDescription": "Lorem ipsum"
  },
  {
    "number": 17,
    "name": "The Star",
    "suit": "major",
    "uprightDescription": "Lorem ipsum",
    "reverseDescription": "Lorem ipsum"
  },
  {
    "number": 18,
    "name": "The Moon",
    "suit": "major",
    "uprightDescription": "Lorem ipsum",
    "reverseDescription": "Lorem ipsum"
  },
  {
    "number": 19,
    "name": "The Sun",
    "suit": "major",
    "uprightDescription": "Lorem ipsum",
    "reverseDescription": "Lorem ipsum"
  },
  {
    "number": 20,
    "name": "Judgement",
    "suit": "major",
    "uprightDescription": "Lorem ipsum",
    "reverseDescription": "Lorem ipsum"
  },
  {
    "number": 21,
    "name": "The World",
    "suit": "major",
    "uprightDescription": "Lorem ipsum",
    "reverseDescription": "Lorem ipsum"
  }
]